{"people":[{"id":"UGVyc29uOjA=","firstName":"Malvina","lastName":"Windler","city":"North Tesston","state":"MI","country":"Liechtenstein"},{"id":"UGVyc29uOjE=","firstName":"Ciara","lastName":"Schultz","city":"New Maximillian","state":"NV","country":"Bouvet Island (Bouvetoya)"},{"id":"UGVyc29uOjI=","firstName":"Dora","lastName":"Stoltenberg","city":"Port Mertieview","state":"NV","country":"Republic of Korea"},{"id":"UGVyc29uOjM=","firstName":"Deonte","lastName":"Schmidt","city":"East Raina","state":"OK","country":"Iceland"},{"id":"UGVyc29uOjQ=","firstName":"Elliot","lastName":"Schoen","city":"West Esther","state":"RI","country":"Estonia"},{"id":"UGVyc29uOjU=","firstName":"Princess","lastName":"Kerluke","city":"Port Mariahstad","state":"VA","country":"French Polynesia"},{"id":"UGVyc29uOjY=","firstName":"Arvel","lastName":"Johnson","city":"Leschview","state":"GA","country":"Saudi Arabia"},{"id":"UGVyc29uOjc=","firstName":"Roma","lastName":"Ritchie","city":"Lucindaton","state":"ND","country":"Togo"},{"id":"UGVyc29uOjg=","firstName":"Meda","lastName":"Lynch","city":"East Janport","state":"WV","country":"Mali"},{"id":"UGVyc29uOjk=","firstName":"Javonte","lastName":"Wilderman","city":"Runteland","state":"MO","country":"Hong Kong"},{"id":"UGVyc29uOjEw","firstName":"Donald","lastName":"Stoltenberg","city":"East Earnestville","state":"MA","country":"Maldives"},{"id":"UGVyc29uOjEx","firstName":"Isai","lastName":"Gerhold","city":"Port Aimeemouth","state":"NC","country":"Democratic People's Republic of Korea"},{"id":"UGVyc29uOjEy","firstName":"Katlyn","lastName":"Ferry","city":"Rogersville","state":"NE","country":"Israel"},{"id":"UGVyc29uOjEz","firstName":"Alexandria","lastName":"Cummings","city":"Port Lelah","state":"UT","country":"Chile"},{"id":"UGVyc29uOjE0","firstName":"Devan","lastName":"Lindgren","city":"Claudiemouth","state":"NJ","country":"Burundi"},{"id":"UGVyc29uOjE1","firstName":"Leonel","lastName":"Pacocha","city":"Stiedemannport","state":"MD","country":"Ghana"},{"id":"UGVyc29uOjE2","firstName":"Nyasia","lastName":"Nienow","city":"Shanieberg","state":"NE","country":"Guam"},{"id":"UGVyc29uOjE3","firstName":"Evalyn","lastName":"Wehner","city":"Hintzland","state":"WI","country":"Zambia"},{"id":"UGVyc29uOjE4","firstName":"Sherman","lastName":"Ziemann","city":"Port Agustin","state":"GA","country":"Latvia"},{"id":"UGVyc29uOjE5","firstName":"Candelario","lastName":"Davis","city":"West Columbusbury","state":"WI","country":"South Georgia and the South Sandwich Islands"},{"id":"UGVyc29uOjIw","firstName":"Cortney","lastName":"Rowe","city":"Port Arnoldshire","state":"VT","country":"Congo"},{"id":"UGVyc29uOjIx","firstName":"Ted","lastName":"Emard","city":"Celestinomouth","state":"CT","country":"Saint Barthelemy"},{"id":"UGVyc29uOjIy","firstName":"Dejon","lastName":"Nolan","city":"Turnertown","state":"AZ","country":"Antigua and Barbuda"},{"id":"UGVyc29uOjIz","firstName":"Maximilian","lastName":"Auer","city":"West Edwin","state":"AR","country":"Greece"},{"id":"UGVyc29uOjI0","firstName":"Karolann","lastName":"Grant","city":"New Margarette","state":"NE","country":"Cocos (Keeling) Islands"},{"id":"UGVyc29uOjI1","firstName":"Rebekah","lastName":"Schinner","city":"Toyborough","state":"HI","country":"Moldova"},{"id":"UGVyc29uOjI2","firstName":"London","lastName":"Schmidt","city":"Alberthaside","state":"WI","country":"Croatia"},{"id":"UGVyc29uOjI3","firstName":"Nannie","lastName":"Stamm","city":"Donnellyfort","state":"MI","country":"New Zealand"},{"id":"UGVyc29uOjI4","firstName":"Raheem","lastName":"Harber","city":"New Allen","state":"MO","country":"Madagascar"},{"id":"UGVyc29uOjI5","firstName":"Garnet","lastName":"Swaniawski","city":"Aufderharshire","state":"NH","country":"Botswana"},{"id":"UGVyc29uOjMw","firstName":"Mylene","lastName":"Stokes","city":"Danview","state":"UT","country":"Dominican Republic"},{"id":"UGVyc29uOjMx","firstName":"Thelma","lastName":"Metz","city":"North Heberstad","state":"OR","country":"Dominica"},{"id":"UGVyc29uOjMy","firstName":"Sherwood","lastName":"Kuvalis","city":"East Grace","state":"NY","country":"Seychelles"},{"id":"UGVyc29uOjMz","firstName":"Heidi","lastName":"Hickle","city":"Zoraburgh","state":"UT","country":"Jamaica"},{"id":"UGVyc29uOjM0","firstName":"Rodrigo","lastName":"Hartmann","city":"Jameyberg","state":"NH","country":"Cape Verde"},{"id":"UGVyc29uOjM1","firstName":"Janelle","lastName":"Corwin","city":"Jeromeside","state":"CA","country":"Chad"},{"id":"UGVyc29uOjM2","firstName":"Keagan","lastName":"Halvorson","city":"Jaylenland","state":"OK","country":"Pakistan"},{"id":"UGVyc29uOjM3","firstName":"Stefanie","lastName":"Feeney","city":"Trevionborough","state":"MN","country":"Palestinian Territory"},{"id":"UGVyc29uOjM4","firstName":"Mariano","lastName":"Erdman","city":"Port Aileenchester","state":"NC","country":"Ukraine"},{"id":"UGVyc29uOjM5","firstName":"Dan","lastName":"Ratke","city":"Alland","state":"NE","country":"Brunei Darussalam"}],"events":[{"id":"0","name":"Lightning Talks","date":"2017-09-21T19:46:31.281Z","place":3,"details":"In this meet, we hope to explore connecting online feeds."},{"id":"1","name":"Lightning Talks","date":"2017-10-25T07:08:21.654Z","place":19,"details":"In this meet, we hope to explore backing up neural buss."},{"id":"2","name":"Electronics, Microcontroller and IOT Evening","date":"2017-11-02T08:13:38.203Z","place":44,"details":"In this meet, we hope to explore programming virtual feeds."},{"id":"3","name":"Coder Forge @ DFC - learn and code, then code some more","date":"2017-06-27T16:27:23.065Z","place":62,"details":"A interesting talk on indexing PCI sensors."},{"id":"4","name":"Nodeschool 13","date":"2017-08-12T08:41:49.492Z","place":48,"details":"Join us in a presentation led by Tyrese Stamm on IB."},{"id":"5","name":"Cork|Sec Meetup 47","date":"2018-02-11T23:51:43.252Z","place":12,"details":"Join us in a hackathon led by Tiana Weissnat V on EXE."},{"id":"6","name":"VueJS & Augmented Reality with JS","date":"2017-06-03T15:55:29.762Z","place":82,"details":"Join us in a talk led by Ryleigh Kunde on PCI."},{"id":"7","name":"Harvey Nash Technology Live! are hosting our First Meet-UP!","date":"2017-03-23T09:02:43.780Z","place":37,"details":"In this meet, we hope to explore copying back-end arrays."},{"id":"8","name":"Coder Forge @ DFC - learn and code, then code some more","date":"2017-06-17T23:31:01.932Z","place":2,"details":"A interesting hackathon on indexing RSS sensors."},{"id":"9","name":"CodePenDublin [#3]: Show and Tell at Trinity","date":"2017-05-18T05:15:40.731Z","place":87,"details":"In this meet, we hope to explore compressing mobile hard drives."},{"id":"10","name":"Nodeschool 13","date":"2017-04-29T15:26:57.775Z","place":77,"details":"In this meet, we hope to explore compressing online arrays."},{"id":"11","name":"⚓🔆 Labor Day Weekend - Sailing The Netherlands 🔆⚓","date":"2017-03-17T11:34:26.558Z","place":86,"details":"Join us in a presentation led by Dr. Drake Glover on PCI."},{"id":"12","name":"Nodeschool 13","date":"2017-07-06T20:26:17.967Z","place":91,"details":"What does a District Applications Consultant do? Learn from Freeman Murphy in this forward-looking talk."},{"id":"13","name":"Cork|Sec Meetup 47","date":"2017-09-01T17:07:40.540Z","place":79,"details":"In this meet, we hope to explore parsing haptic bandwidths."},{"id":"14","name":"Electronics, Microcontroller and IOT Evening","date":"2017-08-31T09:55:44.720Z","place":81,"details":"What does a Future Operations Supervisor do? Learn from Lucile Willms in this pathetic discussion."},{"id":"15","name":"GDG Dublin - Google Cloud Next'17 Extended - Live Keynote","date":"2017-05-11T14:59:32.679Z","place":76,"details":"What does a Internal Functionality Coordinator do? Learn from Gabe Stanton in this engaging talk."},{"id":"16","name":"Coder Forge @ DFC - learn and code, then code some more","date":"2017-12-22T13:59:24.767Z","place":12,"details":"Join us in a hackathon led by Ludie Pagac I on SQL."},{"id":"17","name":"Harvey Nash Technology Live! are hosting our First Meet-UP!","date":"2017-05-14T08:44:11.750Z","place":51,"details":"What does a Dynamic Program Executive do? Learn from Precious Koss in this engaging hackathon."},{"id":"18","name":"PyData Italy and PyData London","date":"2017-09-09T03:50:06.155Z","place":60,"details":"Join us in a talk led by Arden Orn on SMTP."},{"id":"19","name":"Java Language and Platform Futures: A Sneak Peek","date":"2017-11-10T07:33:46.842Z","place":87,"details":"In this meet, we hope to explore parsing 1080p microchips."},{"id":"20","name":"Harvey Nash Technology Live! are hosting our First Meet-UP!","date":"2017-03-31T21:01:15.027Z","place":35,"details":"What does a Human Program Assistant do? Learn from Donato Stracke DDS in this fascinating hackathon."},{"id":"21","name":"Cork|Sec Meetup 47","date":"2018-02-16T11:13:13.652Z","place":73,"details":"A fascinating talk on indexing IB feeds."},{"id":"22","name":"Nodeschool 13","date":"2017-07-12T11:50:35.186Z","place":45,"details":"A forward-looking presentation on overriding SSL alarms."},{"id":"23","name":"Cork|Sec Meetup 47","date":"2017-09-25T06:42:46.379Z","place":91,"details":"What does a Corporate Infrastructure Developer do? Learn from Breanna Bednar in this fascinating talk."},{"id":"24","name":"Dublin Software Craftsmanship Community","date":"2017-04-29T15:22:12.671Z","place":67,"details":"Join us in a talk led by Piper Dooley on PNG."},{"id":"25","name":"GDG Dublin - Google Cloud Next'17 Extended - Live Keynote","date":"2017-08-19T14:00:31.412Z","place":83,"details":"In this meet, we hope to explore copying solid state programs."},{"id":"26","name":"Regular Meetup","date":"2017-03-24T21:08:52.324Z","place":62,"details":"A fascinating hackathon on navigating CSS pixels."},{"id":"27","name":"Integrating the Extended Enterprise with Red Hat JBoss Fuse Breakfast Briefing","date":"2018-01-12T21:21:13.563Z","place":96,"details":"What does a Customer Infrastructure Officer do? Learn from Molly Schuppe in this forward-looking discussion."},{"id":"28","name":"PyData Italy and PyData London","date":"2017-11-16T18:22:25.642Z","place":79,"details":"A interesting talk on quantifying CSS arrays."},{"id":"29","name":"Java Language and Platform Futures: A Sneak Peek","date":"2017-06-12T07:57:36.327Z","place":34,"details":"What does a Dynamic Quality Developer do? Learn from Ivah Fisher in this compelling talk."},{"id":"30","name":"StartupBlink April Networking event","date":"2017-04-02T13:11:22.590Z","place":56,"details":"Join us in a discussion led by Deontae Wisozk IV on SSL."},{"id":"31","name":"Java Language and Platform Futures: A Sneak Peek","date":"2017-11-04T15:12:52.057Z","place":81,"details":"What does a District Solutions Agent do? Learn from Madeline Spinka in this engaging hackathon."},{"id":"32","name":"Electronics, Microcontroller and IOT Evening","date":"2017-08-16T07:49:50.494Z","place":56,"details":"A compelling hackathon on connecting SMTP cards."},{"id":"33","name":"⚓🔆 Labor Day Weekend - Sailing The Netherlands 🔆⚓","date":"2017-09-10T00:52:55.997Z","place":16,"details":"What does a International Directives Developer do? Learn from Kale Connelly in this engaging hackathon."},{"id":"34","name":"Integrating the Extended Enterprise with Red Hat JBoss Fuse Breakfast Briefing","date":"2017-05-29T12:25:48.024Z","place":73,"details":"What does a Product Solutions Associate do? Learn from Chad Bayer in this compelling talk."},{"id":"35","name":"DublinJS Meetup @ Intercom","date":"2017-12-17T05:23:38.087Z","place":98,"details":"A upbeat discussion on quantifying SMS bandwidths."},{"id":"36","name":"Java Language and Platform Futures: A Sneak Peek","date":"2017-07-15T05:43:42.113Z","place":25,"details":"What does a Principal Usability Planner do? Learn from Bethel McCullough in this interesting hackathon."},{"id":"37","name":"Integrating the Extended Enterprise with Red Hat JBoss Fuse Breakfast Briefing","date":"2017-08-13T03:24:53.251Z","place":82,"details":"A interesting hackathon on synthesizing SMS systems."},{"id":"38","name":"Integrating the Extended Enterprise with Red Hat JBoss Fuse Breakfast Briefing","date":"2018-03-15T09:47:21.089Z","place":17,"details":"A fascinating talk on synthesizing SMS panels."},{"id":"39","name":"PyData Italy and PyData London","date":"2017-03-21T00:50:45.436Z","place":12,"details":"A upbeat presentation on transmitting CSS programs."},{"id":"40","name":"PyData Italy and PyData London","date":"2017-06-16T08:13:26.584Z","place":22,"details":"In this meet, we hope to explore connecting wireless protocols."},{"id":"41","name":"Cork|Sec Meetup 47","date":"2018-02-04T17:33:56.116Z","place":55,"details":"Join us in a hackathon led by Forrest Swaniawski on RSS."},{"id":"42","name":"CodePenDublin [#3]: Show and Tell at Trinity","date":"2017-07-24T06:31:23.632Z","place":48,"details":"Join us in a talk led by Camron Yundt on XSS."},{"id":"43","name":"⚓🔆 Labor Day Weekend - Sailing The Netherlands 🔆⚓","date":"2018-01-23T23:17:44.736Z","place":58,"details":"What does a Principal Interactions Administrator do? Learn from Derek Reilly in this fascinating presentation."},{"id":"44","name":"Regular Meetup","date":"2018-01-10T23:51:08.089Z","place":76,"details":"In this meet, we hope to explore connecting back-end panels."},{"id":"45","name":"PyLadies Dublin Meetup","date":"2018-02-27T12:14:59.182Z","place":48,"details":"Join us in a talk led by Grant Kreiger II on COM."},{"id":"46","name":"Integrating the Extended Enterprise with Red Hat JBoss Fuse Breakfast Briefing","date":"2017-07-12T02:21:36.904Z","place":65,"details":"In this meet, we hope to explore copying bluetooth interfaces."},{"id":"47","name":"Regular Meetup","date":"2017-12-19T00:14:26.965Z","place":19,"details":"What does a Central Infrastructure Facilitator do? Learn from Mr. Susanna Denesik in this compelling discussion."},{"id":"48","name":"Electronics, Microcontroller and IOT Evening","date":"2017-08-13T12:06:03.991Z","place":88,"details":"In this meet, we hope to explore navigating optical drivers."},{"id":"49","name":"March Katas!","date":"2017-11-01T13:12:10.171Z","place":99,"details":"Join us in a discussion led by Elouise Kertzmann on SSL."},{"id":"50","name":"PyData Italy and PyData London","date":"2017-11-29T00:15:30.604Z","place":35,"details":"What does a Customer Branding Architect do? Learn from Nelle Mann in this engaging discussion."},{"id":"51","name":"Lightning Talks","date":"2017-03-25T03:08:06.790Z","place":57,"details":"A fascinating discussion on navigating GB bandwidths."},{"id":"52","name":"CodePenDublin [#3]: Show and Tell at Trinity","date":"2018-02-01T17:08:31.856Z","place":72,"details":"In this meet, we hope to explore calculating back-end protocols."},{"id":"53","name":"Lightning Talks","date":"2017-08-26T01:00:14.714Z","place":85,"details":"Join us in a hackathon led by Kiel Grimes on HTTP."},{"id":"54","name":"Dublin Java User Group - Monthly Event","date":"2017-06-26T04:19:26.587Z","place":61,"details":"Join us in a discussion led by Daryl Hintz on SMTP."},{"id":"55","name":"Electronics, Microcontroller and IOT Evening","date":"2017-05-09T20:31:00.204Z","place":31,"details":"Join us in a presentation led by Liliane Ward on XSS."},{"id":"56","name":"Dublin Software Craftsmanship Community","date":"2017-06-25T20:12:35.497Z","place":81,"details":"Join us in a talk led by Amelia Schuster on XML."},{"id":"57","name":"Java Language and Platform Futures: A Sneak Peek","date":"2017-10-11T22:02:57.597Z","place":12,"details":"In this meet, we hope to explore overriding open-source buss."},{"id":"58","name":"Java Language and Platform Futures: A Sneak Peek","date":"2017-12-29T17:09:40.891Z","place":43,"details":"In this meet, we hope to explore navigating digital microchips."},{"id":"59","name":"Integrating the Extended Enterprise with Red Hat JBoss Fuse Breakfast Briefing","date":"2017-11-11T18:30:24.181Z","place":21,"details":"What does a Future Quality Engineer do? Learn from Ms. Angelina Rutherford in this forward-looking discussion."},{"id":"60","name":"Regular Meetup","date":"2017-07-21T00:52:58.201Z","place":56,"details":"In this meet, we hope to explore hacking wireless firewalls."},{"id":"61","name":"Lightning Talks","date":"2017-04-15T15:31:17.400Z","place":69,"details":"A compelling hackathon on generating FTP microchips."},{"id":"62","name":"Dublin Software Craftsmanship Community","date":"2017-10-22T07:53:08.604Z","place":79,"details":"Join us in a presentation led by Miss Randal Breitenberg on FTP."},{"id":"63","name":"Java Language and Platform Futures: A Sneak Peek","date":"2017-07-24T03:49:26.219Z","place":22,"details":"A fascinating talk on transmitting PNG applications."},{"id":"64","name":"VueJS & Augmented Reality with JS","date":"2017-10-30T07:58:29.066Z","place":60,"details":"Join us in a presentation led by Rickie Conroy on AI."},{"id":"65","name":"Integrating the Extended Enterprise with Red Hat JBoss Fuse Breakfast Briefing","date":"2017-11-26T07:45:30.913Z","place":16,"details":"Join us in a hackathon led by Mrs. Phyllis Grady on SMS."},{"id":"66","name":"Electronics, Microcontroller and IOT Evening","date":"2017-11-13T12:22:14.605Z","place":94,"details":"In this meet, we hope to explore synthesizing open-source systems."},{"id":"67","name":"VueJS & Augmented Reality with JS","date":"2017-08-29T06:47:05.547Z","place":80,"details":"A upbeat presentation on transmitting PNG drivers."},{"id":"68","name":"PyLadies Dublin Meetup","date":"2017-06-03T18:05:51.257Z","place":81,"details":"In this meet, we hope to explore indexing solid state bandwidths."},{"id":"69","name":"⚓🔆 Labor Day Weekend - Sailing The Netherlands 🔆⚓","date":"2018-03-07T04:59:22.399Z","place":73,"details":"What does a Future Program Producer do? Learn from Buck Haley in this astounding talk."},{"id":"70","name":"Integrating the Extended Enterprise with Red Hat JBoss Fuse Breakfast Briefing","date":"2017-11-10T13:52:32.283Z","place":68,"details":"A fascinating talk on transmitting TCP transmitters."},{"id":"71","name":"Dublin Java User Group - Monthly Event","date":"2017-06-10T06:45:30.629Z","place":89,"details":"Join us in a discussion led by Favian Wintheiser on SSL."},{"id":"72","name":"Harvey Nash Technology Live! are hosting our First Meet-UP!","date":"2017-05-14T22:34:15.204Z","place":10,"details":"What does a Lead Tactics Developer do? Learn from Eden Rempel in this pathetic presentation."},{"id":"73","name":"VueJS & Augmented Reality with JS","date":"2017-07-25T19:01:08.839Z","place":89,"details":"In this meet, we hope to explore synthesizing bluetooth buss."},{"id":"74","name":"CodePenDublin [#3]: Show and Tell at Trinity","date":"2017-05-17T15:48:26.847Z","place":28,"details":"Join us in a presentation led by Dr. Isac Klein on PNG."},{"id":"75","name":"CodePenDublin [#3]: Show and Tell at Trinity","date":"2017-09-17T13:44:40.989Z","place":2,"details":"What does a Lead Infrastructure Assistant do? Learn from Jakob Emard in this fascinating presentation."},{"id":"76","name":"StartupBlink April Networking event","date":"2018-01-07T12:27:33.967Z","place":4,"details":"A forward-looking talk on overriding AGP capacitors."},{"id":"77","name":"Electronics, Microcontroller and IOT Evening","date":"2017-08-20T22:30:50.274Z","place":2,"details":"In this meet, we hope to explore programming neural interfaces."},{"id":"78","name":"March Katas!","date":"2017-10-11T17:06:40.968Z","place":34,"details":"What does a Human Accountability Developer do? Learn from Simeon Batz in this compelling talk."},{"id":"79","name":"CodePenDublin [#3]: Show and Tell at Trinity","date":"2018-02-07T16:08:26.663Z","place":49,"details":"Join us in a talk led by Jo Kreiger on CSS."},{"id":"80","name":"Integrating the Extended Enterprise with Red Hat JBoss Fuse Breakfast Briefing","date":"2017-07-11T15:13:43.632Z","place":39,"details":"What does a Future Directives Liaison do? Learn from Justina Christiansen in this interesting hackathon."},{"id":"81","name":"AWS Usergroup Dublin MeetUp #21","date":"2017-08-07T13:45:20.267Z","place":35,"details":"What does a Regional Research Assistant do? Learn from Judah O'Connell in this upbeat presentation."},{"id":"82","name":"Regular Meetup","date":"2017-08-01T09:24:02.310Z","place":67,"details":"What does a Senior Division Manager do? Learn from Benton Becker in this upbeat talk."},{"id":"83","name":"Nodeschool 13","date":"2017-10-09T12:48:29.861Z","place":18,"details":"In this meet, we hope to explore calculating redundant applications."},{"id":"84","name":"⚓🔆 Labor Day Weekend - Sailing The Netherlands 🔆⚓","date":"2017-08-05T22:48:15.177Z","place":58,"details":"What does a District Identity Agent do? Learn from Ulises Kirlin in this interesting talk."},{"id":"85","name":"Java Language and Platform Futures: A Sneak Peek","date":"2017-06-24T09:17:20.748Z","place":49,"details":"A fascinating hackathon on indexing GB pixels."},{"id":"86","name":"Java Language and Platform Futures: A Sneak Peek","date":"2018-03-07T01:16:01.142Z","place":88,"details":"What does a Future Quality Assistant do? Learn from Tatyana Thiel in this engaging discussion."},{"id":"87","name":"GDG Dublin - Google Cloud Next'17 Extended - Live Keynote","date":"2017-04-18T09:10:54.311Z","place":94,"details":"In this meet, we hope to explore programming open-source transmitters."},{"id":"88","name":"Regular Meetup","date":"2017-10-01T21:22:26.478Z","place":32,"details":"What does a Central Brand Coordinator do? Learn from Ransom McCullough in this engaging presentation."},{"id":"89","name":"Nodeschool 13","date":"2017-05-30T05:35:12.407Z","place":92,"details":"A compelling presentation on backing up XML cards."},{"id":"90","name":"Electronics, Microcontroller and IOT Evening","date":"2017-06-11T22:19:48.897Z","place":4,"details":"Join us in a talk led by Camden Greenfelder on SMTP."},{"id":"91","name":"Java Language and Platform Futures: A Sneak Peek","date":"2018-02-17T13:47:27.987Z","place":36,"details":"What does a Product Research Developer do? Learn from Maud Abernathy DVM in this interesting talk."},{"id":"92","name":"Integrating the Extended Enterprise with Red Hat JBoss Fuse Breakfast Briefing","date":"2017-11-30T09:20:48.854Z","place":27,"details":"What does a Internal Group Planner do? Learn from May Shanahan in this compelling discussion."},{"id":"93","name":"March Katas!","date":"2017-10-03T21:15:49.069Z","place":93,"details":"In this meet, we hope to explore navigating wireless circuits."},{"id":"94","name":"AWS Usergroup Dublin MeetUp #21","date":"2018-02-09T13:55:02.949Z","place":36,"details":"Join us in a hackathon led by Tomas Schuppe on XML."},{"id":"95","name":"VueJS & Augmented Reality with JS","date":"2017-08-06T14:15:06.226Z","place":14,"details":"In this meet, we hope to explore overriding neural feeds."},{"id":"96","name":"VueJS & Augmented Reality with JS","date":"2017-09-21T07:28:00.151Z","place":9,"details":"In this meet, we hope to explore compressing mobile protocols."},{"id":"97","name":"Dublin Software Craftsmanship Community","date":"2017-11-14T13:15:05.617Z","place":42,"details":"A interesting hackathon on calculating COM ports."},{"id":"98","name":"AWS Usergroup Dublin MeetUp #21","date":"2017-03-31T11:05:54.015Z","place":59,"details":"In this meet, we hope to explore connecting optical microchips."},{"id":"99","name":"Regular Meetup","date":"2018-02-03T17:48:43.604Z","place":24,"details":"What does a Future Operations Technician do? Learn from Reggie D'Amore in this fascinating talk."},{"id":"100","name":"March Katas!","date":"2017-04-08T15:35:38.872Z","place":51,"details":"In this meet, we hope to explore backing up haptic ports."},{"id":"101","name":"Harvey Nash Technology Live! are hosting our First Meet-UP!","date":"2017-07-31T09:45:01.272Z","place":11,"details":"What does a Global Configuration Director do? Learn from Evan McGlynn in this interesting talk."},{"id":"102","name":"Electronics, Microcontroller and IOT Evening","date":"2017-07-23T05:46:29.741Z","place":66,"details":"What does a District Infrastructure Planner do? Learn from Miss Telly Brekke in this engaging discussion."},{"id":"103","name":"GDG Dublin - Google Cloud Next'17 Extended - Live Keynote","date":"2017-07-06T02:57:27.936Z","place":25,"details":"Join us in a presentation led by Mr. Adriel Howell on JSON."},{"id":"104","name":"PyData Italy and PyData London","date":"2017-11-27T08:18:51.287Z","place":99,"details":"Join us in a presentation led by Collin Toy on PCI."},{"id":"105","name":"PyLadies Dublin Meetup","date":"2017-06-15T13:00:44.147Z","place":85,"details":"What does a Dynamic Creative Agent do? Learn from Doyle Nienow PhD in this fascinating talk."},{"id":"106","name":"PyData Italy and PyData London","date":"2017-09-11T06:46:53.383Z","place":64,"details":"A forward-looking talk on calculating EXE drivers."},{"id":"107","name":"StartupBlink April Networking event","date":"2017-04-13T08:13:58.428Z","place":76,"details":"Join us in a discussion led by Enrico Bergstrom on GB."},{"id":"108","name":"GDG Dublin - Google Cloud Next'17 Extended - Live Keynote","date":"2017-08-03T22:37:29.086Z","place":78,"details":"Join us in a discussion led by Felicity Paucek on AI."},{"id":"109","name":"PyData Italy and PyData London","date":"2017-07-19T16:33:54.364Z","place":38,"details":"A compelling hackathon on navigating JSON systems."},{"id":"110","name":"StartupBlink April Networking event","date":"2017-05-21T13:11:28.040Z","place":64,"details":"In this meet, we hope to explore quantifying online matrixs."},{"id":"111","name":"CodePenDublin [#3]: Show and Tell at Trinity","date":"2017-08-08T14:12:10.121Z","place":9,"details":"What does a Customer Solutions Analyst do? Learn from Mr. Noemie Jacobs in this astounding presentation."},{"id":"112","name":"Regular Meetup","date":"2017-08-31T13:47:37.666Z","place":84,"details":"Join us in a presentation led by Ms. Gerhard Grady on XML."},{"id":"113","name":"DublinJS Meetup @ Intercom","date":"2018-01-27T12:57:29.080Z","place":17,"details":"In this meet, we hope to explore parsing digital panels."},{"id":"114","name":"Coder Forge @ DFC - learn and code, then code some more","date":"2017-11-01T01:11:21.279Z","place":47,"details":"What does a Central Configuration Liaison do? Learn from Princess Altenwerth II in this interesting discussion."},{"id":"115","name":"Harvey Nash Technology Live! are hosting our First Meet-UP!","date":"2018-01-04T02:03:49.176Z","place":44,"details":"Join us in a presentation led by Tyrique Volkman on HDD."},{"id":"116","name":"Coder Forge @ DFC - learn and code, then code some more","date":"2017-07-26T12:36:02.094Z","place":68,"details":"In this meet, we hope to explore parsing solid state hard drives."},{"id":"117","name":"Electronics, Microcontroller and IOT Evening","date":"2017-09-11T12:00:10.942Z","place":73,"details":"A fascinating discussion on compressing USB programs."},{"id":"118","name":"Regular Meetup","date":"2017-05-09T17:20:47.795Z","place":51,"details":"Join us in a presentation led by Lempi Armstrong on PNG."},{"id":"119","name":"Dublin Software Craftsmanship Community","date":"2017-11-30T12:47:32.751Z","place":11,"details":"Join us in a presentation led by Guiseppe Rowe on SCSI."},{"id":"120","name":"Nodeschool 13","date":"2017-09-08T05:36:03.768Z","place":37,"details":"Join us in a presentation led by Gisselle Green on HDD."},{"id":"121","name":"GDG Dublin - Google Cloud Next'17 Extended - Live Keynote","date":"2017-12-19T00:43:48.384Z","place":96,"details":"What does a Lead Intranet Designer do? Learn from Julie VonRueden V in this fascinating hackathon."},{"id":"122","name":"Electronics, Microcontroller and IOT Evening","date":"2017-07-07T05:03:26.882Z","place":45,"details":"What does a Dynamic Assurance Administrator do? Learn from Glen Nolan in this forward-looking presentation."},{"id":"123","name":"PyLadies Dublin Meetup","date":"2017-08-12T08:31:50.526Z","place":20,"details":"A engaging talk on parsing JBOD drivers."},{"id":"124","name":"Integrating the Extended Enterprise with Red Hat JBoss Fuse Breakfast Briefing","date":"2017-05-19T02:13:05.792Z","place":93,"details":"Join us in a talk led by Reynold Bauch on THX."},{"id":"125","name":"PyData Italy and PyData London","date":"2018-02-28T19:32:16.254Z","place":0,"details":"What does a Central Marketing Designer do? Learn from Dr. Wilfrid Spencer in this astounding presentation."},{"id":"126","name":"VueJS & Augmented Reality with JS","date":"2017-12-12T09:49:09.251Z","place":93,"details":"Join us in a presentation led by Ms. Javonte Renner on COM."},{"id":"127","name":"Java Language and Platform Futures: A Sneak Peek","date":"2017-09-29T06:38:04.293Z","place":81,"details":"A upbeat hackathon on copying COM ports."},{"id":"128","name":"StartupBlink April Networking event","date":"2017-05-25T10:14:06.669Z","place":50,"details":"Join us in a talk led by Lisa Dickens V on FTP."},{"id":"129","name":"AWS Usergroup Dublin MeetUp #21","date":"2017-08-19T03:15:41.280Z","place":27,"details":"What does a Central Data Developer do? Learn from Erich Maggio in this interesting hackathon."},{"id":"130","name":"Regular Meetup","date":"2018-03-13T16:46:59.360Z","place":73,"details":"In this meet, we hope to explore programming optical interfaces."},{"id":"131","name":"Java Language and Platform Futures: A Sneak Peek","date":"2017-08-31T07:58:47.303Z","place":11,"details":"What does a Product Mobility Designer do? Learn from Ephraim Wiza in this compelling presentation."},{"id":"132","name":"Regular Meetup","date":"2017-06-14T00:13:56.439Z","place":78,"details":"Join us in a hackathon led by Lelah Schuppe on JSON."},{"id":"133","name":"PyData Italy and PyData London","date":"2017-05-22T22:53:06.557Z","place":0,"details":"A astounding talk on quantifying XML capacitors."},{"id":"134","name":"AWS Usergroup Dublin MeetUp #21","date":"2018-01-28T17:56:38.347Z","place":72,"details":"Join us in a hackathon led by Cyril Grimes on SSL."},{"id":"135","name":"AWS Usergroup Dublin MeetUp #21","date":"2017-07-15T06:58:55.182Z","place":88,"details":"A fascinating discussion on transmitting JBOD protocols."},{"id":"136","name":"Coder Forge @ DFC - learn and code, then code some more","date":"2017-09-30T16:28:58.472Z","place":26,"details":"A compelling talk on quantifying PCI buss."},{"id":"137","name":"Regular Meetup","date":"2017-09-14T23:44:17.842Z","place":86,"details":"In this meet, we hope to explore calculating online protocols."},{"id":"138","name":"⚓🔆 Labor Day Weekend - Sailing The Netherlands 🔆⚓","date":"2017-10-29T01:05:46.431Z","place":11,"details":"Join us in a discussion led by Burdette Considine II on TCP."},{"id":"139","name":"StartupBlink April Networking event","date":"2017-04-18T20:37:05.977Z","place":34,"details":"What does a Principal Directives Executive do? Learn from Agustina Reynolds in this upbeat hackathon."},{"id":"140","name":"⚓🔆 Labor Day Weekend - Sailing The Netherlands 🔆⚓","date":"2017-04-26T09:10:08.109Z","place":57,"details":"Join us in a presentation led by Raoul Miller on USB."},{"id":"141","name":"CodePenDublin [#3]: Show and Tell at Trinity","date":"2017-07-24T03:24:51.176Z","place":53,"details":"In this meet, we hope to explore generating haptic firewalls."},{"id":"142","name":"Harvey Nash Technology Live! are hosting our First Meet-UP!","date":"2017-09-27T11:31:47.751Z","place":73,"details":"In this meet, we hope to explore generating optical arrays."},{"id":"143","name":"Harvey Nash Technology Live! are hosting our First Meet-UP!","date":"2017-04-16T06:06:34.697Z","place":83,"details":"A astounding discussion on indexing CSS transmitters."},{"id":"144","name":"Nodeschool 13","date":"2017-05-05T21:22:33.109Z","place":6,"details":"Join us in a talk led by Ms. Otha Kuhn on JSON."},{"id":"145","name":"Java Language and Platform Futures: A Sneak Peek","date":"2017-05-08T08:46:48.842Z","place":34,"details":"In this meet, we hope to explore connecting digital microchips."},{"id":"146","name":"Coder Forge @ DFC - learn and code, then code some more","date":"2018-01-14T18:36:03.865Z","place":41,"details":"In this meet, we hope to explore navigating multi-byte cards."},{"id":"147","name":"CodePenDublin [#3]: Show and Tell at Trinity","date":"2017-04-17T15:20:15.030Z","place":34,"details":"In this meet, we hope to explore transmitting redundant applications."},{"id":"148","name":"Regular Meetup","date":"2018-03-01T19:34:02.920Z","place":6,"details":"What does a International Quality Analyst do? Learn from Melvin Lakin in this astounding discussion."},{"id":"149","name":"VueJS & Augmented Reality with JS","date":"2017-04-10T13:01:24.612Z","place":83,"details":"Join us in a hackathon led by Watson Satterfield on ADP."},{"id":"150","name":"StartupBlink April Networking event","date":"2018-02-19T16:22:08.731Z","place":26,"details":"In this meet, we hope to explore bypassing digital feeds."},{"id":"151","name":"Regular Meetup","date":"2017-08-27T02:16:53.316Z","place":60,"details":"Join us in a discussion led by Orin Rodriguez II on USB."},{"id":"152","name":"AWS Usergroup Dublin MeetUp #21","date":"2017-04-29T19:25:35.590Z","place":63,"details":"What does a District Optimization Architect do? Learn from Meggie Mitchell in this pathetic presentation."},{"id":"153","name":"VueJS & Augmented Reality with JS","date":"2018-02-23T19:16:22.952Z","place":97,"details":"In this meet, we hope to explore navigating haptic circuits."},{"id":"154","name":"March Katas!","date":"2017-04-19T07:34:06.981Z","place":64,"details":"In this meet, we hope to explore parsing online capacitors."},{"id":"155","name":"Coder Forge @ DFC - learn and code, then code some more","date":"2018-01-26T15:10:30.129Z","place":91,"details":"What does a Direct Implementation Analyst do? Learn from Zola Ortiz in this forward-looking hackathon."},{"id":"156","name":"Cork|Sec Meetup 47","date":"2017-04-28T04:18:17.419Z","place":96,"details":"Join us in a hackathon led by Mavis Lemke on RAM."},{"id":"157","name":"VueJS & Augmented Reality with JS","date":"2017-11-13T19:59:54.587Z","place":46,"details":"Join us in a discussion led by Dr. Russell Mayert on JBOD."},{"id":"158","name":"PyLadies Dublin Meetup","date":"2018-03-09T10:42:04.196Z","place":1,"details":"What does a International Integration Producer do? Learn from Harrison Reichel in this upbeat talk."},{"id":"159","name":"PyData Italy and PyData London","date":"2017-09-16T21:37:35.214Z","place":94,"details":"In this meet, we hope to explore generating primary monitors."},{"id":"160","name":"Electronics, Microcontroller and IOT Evening","date":"2017-08-02T13:17:47.016Z","place":34,"details":"A interesting hackathon on generating HTTP feeds."},{"id":"161","name":"Regular Meetup","date":"2017-10-20T11:16:33.917Z","place":48,"details":"Join us in a presentation led by Pablo Swaniawski on CSS."},{"id":"162","name":"Lightning Talks","date":"2017-10-07T17:05:23.772Z","place":71,"details":"Join us in a discussion led by Pat Lebsack DVM on COM."},{"id":"163","name":"Integrating the Extended Enterprise with Red Hat JBoss Fuse Breakfast Briefing","date":"2017-09-20T06:08:25.962Z","place":53,"details":"Join us in a talk led by Mr. Cecil Bednar on SAS."},{"id":"164","name":"Integrating the Extended Enterprise with Red Hat JBoss Fuse Breakfast Briefing","date":"2017-04-11T15:40:58.419Z","place":37,"details":"What does a Dynamic Response Director do? Learn from Marjolaine Braun in this astounding hackathon."},{"id":"165","name":"PyLadies Dublin Meetup","date":"2017-06-17T07:12:03.299Z","place":44,"details":"Join us in a presentation led by Brandi Heaney on SCSI."},{"id":"166","name":"Regular Meetup","date":"2017-07-30T17:33:23.095Z","place":82,"details":"In this meet, we hope to explore connecting haptic programs."},{"id":"167","name":"VueJS & Augmented Reality with JS","date":"2017-04-30T12:29:45.490Z","place":7,"details":"Join us in a discussion led by Dr. Matilda Weber on SCSI."},{"id":"168","name":"Electronics, Microcontroller and IOT Evening","date":"2017-05-12T14:21:43.512Z","place":81,"details":"In this meet, we hope to explore parsing online matrixs."},{"id":"169","name":"Harvey Nash Technology Live! are hosting our First Meet-UP!","date":"2017-06-29T16:16:09.667Z","place":86,"details":"Join us in a presentation led by Immanuel Lang on SMS."},{"id":"170","name":"Integrating the Extended Enterprise with Red Hat JBoss Fuse Breakfast Briefing","date":"2017-09-11T10:07:25.028Z","place":75,"details":"A compelling discussion on synthesizing IB capacitors."},{"id":"171","name":"Coder Forge @ DFC - learn and code, then code some more","date":"2017-06-18T22:17:16.750Z","place":90,"details":"Join us in a discussion led by Bailey Renner on RSS."},{"id":"172","name":"Dublin Software Craftsmanship Community","date":"2017-03-30T21:05:25.110Z","place":65,"details":"In this meet, we hope to explore overriding optical pixels."},{"id":"173","name":"Regular Meetup","date":"2018-02-18T00:19:00.068Z","place":54,"details":"What does a Direct Tactics Agent do? Learn from Antonia Dickinson in this fascinating presentation."},{"id":"174","name":"March Katas!","date":"2017-07-07T00:42:02.256Z","place":25,"details":"Join us in a presentation led by Lorena Zieme on SAS."},{"id":"175","name":"Lightning Talks","date":"2017-05-27T17:21:07.965Z","place":97,"details":"Join us in a discussion led by Holly Kuhn on COM."},{"id":"176","name":"Coder Forge @ DFC - learn and code, then code some more","date":"2018-03-13T08:25:57.249Z","place":15,"details":"What does a Investor Brand Representative do? Learn from Boris Hane in this astounding presentation."},{"id":"177","name":"DublinJS Meetup @ Intercom","date":"2017-04-02T10:35:34.363Z","place":54,"details":"A pathetic discussion on quantifying FTP monitors."},{"id":"178","name":"March Katas!","date":"2017-10-18T05:59:22.110Z","place":1,"details":"A forward-looking discussion on overriding GB sensors."},{"id":"179","name":"March Katas!","date":"2018-03-11T09:02:29.829Z","place":47,"details":"In this meet, we hope to explore copying redundant transmitters."},{"id":"180","name":"March Katas!","date":"2017-10-18T04:04:20.541Z","place":32,"details":"What does a Future Integration Representative do? Learn from Kali Pacocha in this engaging presentation."},{"id":"181","name":"DublinJS Meetup @ Intercom","date":"2017-07-09T19:58:03.140Z","place":11,"details":"A forward-looking hackathon on indexing TCP interfaces."},{"id":"182","name":"⚓🔆 Labor Day Weekend - Sailing The Netherlands 🔆⚓","date":"2017-10-14T00:18:16.730Z","place":39,"details":"Join us in a discussion led by Enos Batz on FTP."},{"id":"183","name":"Cork|Sec Meetup 47","date":"2017-09-07T02:53:28.292Z","place":51,"details":"A fascinating discussion on parsing SDD systems."},{"id":"184","name":"Harvey Nash Technology Live! are hosting our First Meet-UP!","date":"2017-08-31T19:42:33.587Z","place":21,"details":"What does a Customer Usability Facilitator do? Learn from Alene Durgan in this interesting presentation."},{"id":"185","name":"PyLadies Dublin Meetup","date":"2017-04-11T06:06:55.780Z","place":77,"details":"In this meet, we hope to explore copying solid state ports."},{"id":"186","name":"AWS Usergroup Dublin MeetUp #21","date":"2017-06-17T10:33:38.794Z","place":5,"details":"What does a Internal Directives Architect do? Learn from Margarett Koss in this pathetic presentation."},{"id":"187","name":"Integrating the Extended Enterprise with Red Hat JBoss Fuse Breakfast Briefing","date":"2017-12-05T03:12:07.294Z","place":48,"details":"Join us in a hackathon led by Aaliyah Waelchi MD on CSS."},{"id":"188","name":"Electronics, Microcontroller and IOT Evening","date":"2018-01-26T22:35:26.777Z","place":65,"details":"What does a Chief Usability Representative do? Learn from Roy Paucek in this pathetic discussion."},{"id":"189","name":"Dublin Java User Group - Monthly Event","date":"2017-03-22T01:48:29.651Z","place":13,"details":"A compelling presentation on navigating PCI microchips."},{"id":"190","name":"Java Language and Platform Futures: A Sneak Peek","date":"2017-04-30T23:32:41.044Z","place":32,"details":"A interesting presentation on hacking GB bandwidths."},{"id":"191","name":"Java Language and Platform Futures: A Sneak Peek","date":"2017-09-02T04:06:01.522Z","place":0,"details":"A forward-looking presentation on indexing PCI applications."},{"id":"192","name":"March Katas!","date":"2017-08-16T07:54:37.965Z","place":72,"details":"What does a District Tactics Agent do? Learn from Johnathon Ondricka in this fascinating talk."},{"id":"193","name":"Electronics, Microcontroller and IOT Evening","date":"2017-12-09T02:12:56.590Z","place":73,"details":"In this meet, we hope to explore connecting wireless protocols."},{"id":"194","name":"Nodeschool 13","date":"2017-09-19T07:43:43.178Z","place":66,"details":"Join us in a talk led by Yasmin Mayer on COM."},{"id":"195","name":"Lightning Talks","date":"2017-07-10T16:40:10.314Z","place":73,"details":"What does a Customer Group Liaison do? Learn from Johnson Lebsack IV in this forward-looking talk."},{"id":"196","name":"Electronics, Microcontroller and IOT Evening","date":"2017-03-24T12:57:34.952Z","place":3,"details":"Join us in a hackathon led by Guillermo Krajcik on HTTP."},{"id":"197","name":"⚓🔆 Labor Day Weekend - Sailing The Netherlands 🔆⚓","date":"2017-11-18T23:01:41.138Z","place":10,"details":"What does a International Research Consultant do? Learn from Kiel Hermiston IV in this interesting talk."},{"id":"198","name":"Cork|Sec Meetup 47","date":"2017-07-17T11:48:59.271Z","place":84,"details":"In this meet, we hope to explore calculating multi-byte drivers."},{"id":"199","name":"Java Language and Platform Futures: A Sneak Peek","date":"2018-02-04T15:50:40.896Z","place":81,"details":"A fascinating presentation on navigating CSS monitors."}],"meets":[{"id":"0","name":"Blockchain Technology Laurinebury","address":"944 Rachael Viaduct","homeTown":"Laurinebury","homeCountry":"Barbados","members":[{"id":"UGVyc29uOjM3","firstName":"Stefanie","lastName":"Feeney","city":"Trevionborough","state":"MN","country":"Palestinian Territory"},{"id":"UGVyc29uOjM1","firstName":"Janelle","lastName":"Corwin","city":"Jeromeside","state":"CA","country":"Chad"},{"id":"UGVyc29uOjMy","firstName":"Sherwood","lastName":"Kuvalis","city":"East Grace","state":"NY","country":"Seychelles"}]},{"id":"1","name":"WebRTC Meetup Jamaica","address":"0728 Corwin Lodge","homeTown":"Abbottberg","homeCountry":"Jamaica","members":[{"id":"UGVyc29uOjIz","firstName":"Maximilian","lastName":"Auer","city":"West Edwin","state":"AR","country":"Greece"},{"id":"UGVyc29uOjMw","firstName":"Mylene","lastName":"Stokes","city":"Danview","state":"UT","country":"Dominican Republic"},{"id":"UGVyc29uOjI0","firstName":"Karolann","lastName":"Grant","city":"New Margarette","state":"NE","country":"Cocos (Keeling) Islands"}]},{"id":"2","name":"Heidenreichmouth Scala Users Group","address":"9070 Parker Plaza","homeTown":"Heidenreichmouth","homeCountry":"Turkmenistan","members":[{"id":"UGVyc29uOjMx","firstName":"Thelma","lastName":"Metz","city":"North Heberstad","state":"OR","country":"Dominica"},{"id":"UGVyc29uOjE5","firstName":"Candelario","lastName":"Davis","city":"West Columbusbury","state":"WI","country":"South Georgia and the South Sandwich Islands"},{"id":"UGVyc29uOjI5","firstName":"Garnet","lastName":"Swaniawski","city":"Aufderharshire","state":"NH","country":"Botswana"}]},{"id":"3","name":"Python Libyan Arab Jamahiriya","address":"8385 Terry Stravenue","homeTown":"North Otishaven","homeCountry":"Libyan Arab Jamahiriya","members":[{"id":"UGVyc29uOjM2","firstName":"Keagan","lastName":"Halvorson","city":"Jaylenland","state":"OK","country":"Pakistan"},{"id":"UGVyc29uOjU=","firstName":"Princess","lastName":"Kerluke","city":"Port Mariahstad","state":"VA","country":"French Polynesia"},{"id":"UGVyc29uOjI0","firstName":"Karolann","lastName":"Grant","city":"New Margarette","state":"NE","country":"Cocos (Keeling) Islands"}]},{"id":"4","name":"AngularJS North April","address":"3516 Aufderhar Isle","homeTown":"North April","homeCountry":"Cook Islands","members":[{"id":"UGVyc29uOjIy","firstName":"Dejon","lastName":"Nolan","city":"Turnertown","state":"AZ","country":"Antigua and Barbuda"},{"id":"UGVyc29uOjMx","firstName":"Thelma","lastName":"Metz","city":"North Heberstad","state":"OR","country":"Dominica"},{"id":"UGVyc29uOjIw","firstName":"Cortney","lastName":"Rowe","city":"Port Arnoldshire","state":"VT","country":"Congo"}]},{"id":"5","name":"Nodeschool Dennismouth Meetup","address":"4688 Nikolaus Mountains","homeTown":"Dennismouth","homeCountry":"Czech Republic","members":[{"id":"UGVyc29uOjEz","firstName":"Alexandria","lastName":"Cummings","city":"Port Lelah","state":"UT","country":"Chile"},{"id":"UGVyc29uOjM3","firstName":"Stefanie","lastName":"Feeney","city":"Trevionborough","state":"MN","country":"Palestinian Territory"},{"id":"UGVyc29uOjE2","firstName":"Nyasia","lastName":"Nienow","city":"Shanieberg","state":"NE","country":"Guam"}]},{"id":"6","name":"Annetteberg Scala Users Group","address":"5717 Mueller Spring","homeTown":"Annetteberg","homeCountry":"Latvia","members":[{"id":"UGVyc29uOjMy","firstName":"Sherwood","lastName":"Kuvalis","city":"East Grace","state":"NY","country":"Seychelles"},{"id":"UGVyc29uOjM4","firstName":"Mariano","lastName":"Erdman","city":"Port Aileenchester","state":"NC","country":"Ukraine"},{"id":"UGVyc29uOjIw","firstName":"Cortney","lastName":"Rowe","city":"Port Arnoldshire","state":"VT","country":"Congo"}]},{"id":"7","name":"Durwardfurt WordPress Group","address":"53805 Runolfsdottir Loop","homeTown":"Durwardfurt","homeCountry":"Iran","members":[{"id":"UGVyc29uOjE5","firstName":"Candelario","lastName":"Davis","city":"West Columbusbury","state":"WI","country":"South Georgia and the South Sandwich Islands"},{"id":"UGVyc29uOjM4","firstName":"Mariano","lastName":"Erdman","city":"Port Aileenchester","state":"NC","country":"Ukraine"},{"id":"UGVyc29uOjIw","firstName":"Cortney","lastName":"Rowe","city":"Port Arnoldshire","state":"VT","country":"Congo"}]},{"id":"8","name":"MMUG-East Bertbury","address":"73372 Ron Centers","homeTown":"East Bertbury","homeCountry":"Svalbard & Jan Mayen Islands","members":[{"id":"UGVyc29uOjEy","firstName":"Katlyn","lastName":"Ferry","city":"Rogersville","state":"NE","country":"Israel"},{"id":"UGVyc29uOjA=","firstName":"Malvina","lastName":"Windler","city":"North Tesston","state":"MI","country":"Liechtenstein"},{"id":"UGVyc29uOjE3","firstName":"Evalyn","lastName":"Wehner","city":"Hintzland","state":"WI","country":"Zambia"}]},{"id":"9","name":"New Murltown TypeScript Meetup","address":"858 Weimann Route","homeTown":"New Murltown","homeCountry":"Northern Mariana Islands","members":[{"id":"UGVyc29uOjIx","firstName":"Ted","lastName":"Emard","city":"Celestinomouth","state":"CT","country":"Saint Barthelemy"},{"id":"UGVyc29uOjIy","firstName":"Dejon","lastName":"Nolan","city":"Turnertown","state":"AZ","country":"Antigua and Barbuda"},{"id":"UGVyc29uOjI5","firstName":"Garnet","lastName":"Swaniawski","city":"Aufderharshire","state":"NH","country":"Botswana"}]},{"id":"10","name":"LJC - London Java Community","address":"72023 Hagenes Loop","homeTown":"Marleebury","homeCountry":"Luxembourg","members":[{"id":"UGVyc29uOjI4","firstName":"Raheem","lastName":"Harber","city":"New Allen","state":"MO","country":"Madagascar"},{"id":"UGVyc29uOjM0","firstName":"Rodrigo","lastName":"Hartmann","city":"Jameyberg","state":"NH","country":"Cape Verde"},{"id":"UGVyc29uOjI2","firstName":"London","lastName":"Schmidt","city":"Alberthaside","state":"WI","country":"Croatia"}]},{"id":"11","name":"Couchbase South Elsa","address":"878 Lehner Ramp","homeTown":"South Elsa","homeCountry":"Latvia","members":[{"id":"UGVyc29uOjE2","firstName":"Nyasia","lastName":"Nienow","city":"Shanieberg","state":"NE","country":"Guam"},{"id":"UGVyc29uOjE4","firstName":"Sherman","lastName":"Ziemann","city":"Port Agustin","state":"GA","country":"Latvia"},{"id":"UGVyc29uOjE0","firstName":"Devan","lastName":"Lindgren","city":"Claudiemouth","state":"NJ","country":"Burundi"}]},{"id":"12","name":"MMUG-Macejkovicton","address":"029 Rodolfo Stravenue","homeTown":"Macejkovicton","homeCountry":"Republic of Korea","members":[{"id":"UGVyc29uOjIy","firstName":"Dejon","lastName":"Nolan","city":"Turnertown","state":"AZ","country":"Antigua and Barbuda"},{"id":"UGVyc29uOjMw","firstName":"Mylene","lastName":"Stokes","city":"Danview","state":"UT","country":"Dominican Republic"},{"id":"UGVyc29uOjE5","firstName":"Candelario","lastName":"Davis","city":"West Columbusbury","state":"WI","country":"South Georgia and the South Sandwich Islands"}]},{"id":"13","name":"Sauermouth Salesforce Developer Group","address":"8881 Estrella Creek","homeTown":"Sauermouth","homeCountry":"Guam","members":[{"id":"UGVyc29uOjI3","firstName":"Nannie","lastName":"Stamm","city":"Donnellyfort","state":"MI","country":"New Zealand"},{"id":"UGVyc29uOjI4","firstName":"Raheem","lastName":"Harber","city":"New Allen","state":"MO","country":"Madagascar"},{"id":"UGVyc29uOjI2","firstName":"London","lastName":"Schmidt","city":"Alberthaside","state":"WI","country":"Croatia"}]},{"id":"14","name":"TechMeetup.space","address":"1957 Turcotte Springs","homeTown":"Fionabury","homeCountry":"Gambia","members":[{"id":"UGVyc29uOjE5","firstName":"Candelario","lastName":"Davis","city":"West Columbusbury","state":"WI","country":"South Georgia and the South Sandwich Islands"},{"id":"UGVyc29uOjY=","firstName":"Arvel","lastName":"Johnson","city":"Leschview","state":"GA","country":"Saudi Arabia"},{"id":"UGVyc29uOjEx","firstName":"Isai","lastName":"Gerhold","city":"Port Aimeemouth","state":"NC","country":"Democratic People's Republic of Korea"}]},{"id":"15","name":"Ember.js New Ursula","address":"46104 Coleman Drive","homeTown":"New Ursula","homeCountry":"Burkina Faso","members":[{"id":"UGVyc29uOjM1","firstName":"Janelle","lastName":"Corwin","city":"Jeromeside","state":"CA","country":"Chad"},{"id":"UGVyc29uOjMy","firstName":"Sherwood","lastName":"Kuvalis","city":"East Grace","state":"NY","country":"Seychelles"},{"id":"UGVyc29uOjE1","firstName":"Leonel","lastName":"Pacocha","city":"Stiedemannport","state":"MD","country":"Ghana"}]},{"id":"16","name":"AngularJS West Augustine","address":"100 Rempel Coves","homeTown":"West Augustine","homeCountry":"Hungary","members":[{"id":"UGVyc29uOjIx","firstName":"Ted","lastName":"Emard","city":"Celestinomouth","state":"CT","country":"Saint Barthelemy"},{"id":"UGVyc29uOjA=","firstName":"Malvina","lastName":"Windler","city":"North Tesston","state":"MI","country":"Liechtenstein"},{"id":"UGVyc29uOjM3","firstName":"Stefanie","lastName":"Feeney","city":"Trevionborough","state":"MN","country":"Palestinian Territory"}]},{"id":"17","name":"Entrepreneurs Anonymous New Darrylmouth","address":"05193 Zander Islands","homeTown":"New Darrylmouth","homeCountry":"Ukraine","members":[{"id":"UGVyc29uOjM2","firstName":"Keagan","lastName":"Halvorson","city":"Jaylenland","state":"OK","country":"Pakistan"},{"id":"UGVyc29uOjI0","firstName":"Karolann","lastName":"Grant","city":"New Margarette","state":"NE","country":"Cocos (Keeling) Islands"},{"id":"UGVyc29uOjQ=","firstName":"Elliot","lastName":"Schoen","city":"West Esther","state":"RI","country":"Estonia"}]},{"id":"18","name":"Docker Heidenreichmouth","address":"9070 Parker Plaza","homeTown":"Heidenreichmouth","homeCountry":"Turkmenistan","members":[{"id":"UGVyc29uOjI1","firstName":"Rebekah","lastName":"Schinner","city":"Toyborough","state":"HI","country":"Moldova"},{"id":"UGVyc29uOjA=","firstName":"Malvina","lastName":"Windler","city":"North Tesston","state":"MI","country":"Liechtenstein"},{"id":"UGVyc29uOjM4","firstName":"Mariano","lastName":"Erdman","city":"Port Aileenchester","state":"NC","country":"Ukraine"}]},{"id":"19","name":"North Kalistad Scala Users Group","address":"2748 Bartell Motorway","homeTown":"North Kalistad","homeCountry":"Namibia","members":[{"id":"UGVyc29uOjM0","firstName":"Rodrigo","lastName":"Hartmann","city":"Jameyberg","state":"NH","country":"Cape Verde"},{"id":"UGVyc29uOjI3","firstName":"Nannie","lastName":"Stamm","city":"Donnellyfort","state":"MI","country":"New Zealand"},{"id":"UGVyc29uOjY=","firstName":"Arvel","lastName":"Johnson","city":"Leschview","state":"GA","country":"Saudi Arabia"}]},{"id":"20","name":"West Catharine Node.js Meetup","address":"37972 Jakubowski Summit","homeTown":"West Catharine","homeCountry":"South Africa","members":[{"id":"UGVyc29uOjI1","firstName":"Rebekah","lastName":"Schinner","city":"Toyborough","state":"HI","country":"Moldova"},{"id":"UGVyc29uOjI0","firstName":"Karolann","lastName":"Grant","city":"New Margarette","state":"NE","country":"Cocos (Keeling) Islands"},{"id":"UGVyc29uOjEw","firstName":"Donald","lastName":"Stoltenberg","city":"East Earnestville","state":"MA","country":"Maldives"}]},{"id":"21","name":"API Lake Kali","address":"5553 Keebler Drive","homeTown":"Lake Kali","homeCountry":"Cameroon","members":[{"id":"UGVyc29uOjI1","firstName":"Rebekah","lastName":"Schinner","city":"Toyborough","state":"HI","country":"Moldova"},{"id":"UGVyc29uOjI3","firstName":"Nannie","lastName":"Stamm","city":"Donnellyfort","state":"MI","country":"New Zealand"},{"id":"UGVyc29uOjEy","firstName":"Katlyn","lastName":"Ferry","city":"Rogersville","state":"NE","country":"Israel"}]},{"id":"22","name":"Functional Kubs","address":"38561 Collier Road","homeTown":"West Lexus","homeCountry":"Thailand","members":[{"id":"UGVyc29uOjI=","firstName":"Dora","lastName":"Stoltenberg","city":"Port Mertieview","state":"NV","country":"Republic of Korea"},{"id":"UGVyc29uOjMw","firstName":"Mylene","lastName":"Stokes","city":"Danview","state":"UT","country":"Dominican Republic"},{"id":"UGVyc29uOjE=","firstName":"Ciara","lastName":"Schultz","city":"New Maximillian","state":"NV","country":"Bouvet Island (Bouvetoya)"}]},{"id":"23","name":"South Sheldonfort Node.js Meetup","address":"05932 O'Conner Lodge","homeTown":"South Sheldonfort","homeCountry":"Croatia","members":[{"id":"UGVyc29uOjE0","firstName":"Devan","lastName":"Lindgren","city":"Claudiemouth","state":"NJ","country":"Burundi"},{"id":"UGVyc29uOjM0","firstName":"Rodrigo","lastName":"Hartmann","city":"Jameyberg","state":"NH","country":"Cape Verde"},{"id":"UGVyc29uOjM5","firstName":"Dan","lastName":"Ratke","city":"Alland","state":"NE","country":"Brunei Darussalam"}]},{"id":"24","name":"North Kylafurt C/C++ User Group","address":"989 Keyon Shores","homeTown":"North Kylafurt","homeCountry":"Bhutan","members":[{"id":"UGVyc29uOjQ=","firstName":"Elliot","lastName":"Schoen","city":"West Esther","state":"RI","country":"Estonia"},{"id":"UGVyc29uOjIz","firstName":"Maximilian","lastName":"Auer","city":"West Edwin","state":"AR","country":"Greece"},{"id":"UGVyc29uOjk=","firstName":"Javonte","lastName":"Wilderman","city":"Runteland","state":"MO","country":"Hong Kong"}]},{"id":"25","name":"Tiaview WebGL Meetup","address":"805 Kozey Fall","homeTown":"Tiaview","homeCountry":"Russian Federation","members":[{"id":"UGVyc29uOjk=","firstName":"Javonte","lastName":"Wilderman","city":"Runteland","state":"MO","country":"Hong Kong"},{"id":"UGVyc29uOjMy","firstName":"Sherwood","lastName":"Kuvalis","city":"East Grace","state":"NY","country":"Seychelles"},{"id":"UGVyc29uOjEy","firstName":"Katlyn","lastName":"Ferry","city":"Rogersville","state":"NE","country":"Israel"}]},{"id":"26","name":"South Nickolasfort Java 8 Meetup","address":"896 Velma Manors","homeTown":"South Nickolasfort","homeCountry":"Czech Republic","members":[{"id":"UGVyc29uOjM2","firstName":"Keagan","lastName":"Halvorson","city":"Jaylenland","state":"OK","country":"Pakistan"},{"id":"UGVyc29uOjc=","firstName":"Roma","lastName":"Ritchie","city":"Lucindaton","state":"ND","country":"Togo"},{"id":"UGVyc29uOjM=","firstName":"Deonte","lastName":"Schmidt","city":"East Raina","state":"OK","country":"Iceland"}]},{"id":"27","name":"Lake Olenton WordPress Group","address":"54747 Hilda Street","homeTown":"Lake Olenton","homeCountry":"San Marino","members":[{"id":"UGVyc29uOjIw","firstName":"Cortney","lastName":"Rowe","city":"Port Arnoldshire","state":"VT","country":"Congo"},{"id":"UGVyc29uOjEz","firstName":"Alexandria","lastName":"Cummings","city":"Port Lelah","state":"UT","country":"Chile"},{"id":"UGVyc29uOjEx","firstName":"Isai","lastName":"Gerhold","city":"Port Aimeemouth","state":"NC","country":"Democratic People's Republic of Korea"}]},{"id":"28","name":"Blockchain Technology Lake Eliton","address":"148 Ebert Ferry","homeTown":"Lake Eliton","homeCountry":"Iceland","members":[{"id":"UGVyc29uOjg=","firstName":"Meda","lastName":"Lynch","city":"East Janport","state":"WV","country":"Mali"},{"id":"UGVyc29uOjEy","firstName":"Katlyn","lastName":"Ferry","city":"Rogersville","state":"NE","country":"Israel"},{"id":"UGVyc29uOjMx","firstName":"Thelma","lastName":"Metz","city":"North Heberstad","state":"OR","country":"Dominica"}]},{"id":"29","name":"ReactJS South Michelle","address":"1662 Becker Points","homeTown":"South Michelle","homeCountry":"Bosnia and Herzegovina","members":[{"id":"UGVyc29uOjEw","firstName":"Donald","lastName":"Stoltenberg","city":"East Earnestville","state":"MA","country":"Maldives"},{"id":"UGVyc29uOjMx","firstName":"Thelma","lastName":"Metz","city":"North Heberstad","state":"OR","country":"Dominica"},{"id":"UGVyc29uOjMw","firstName":"Mylene","lastName":"Stokes","city":"Danview","state":"UT","country":"Dominican Republic"}]},{"id":"30","name":"Lake Kali μServices (Microservices) User Group","address":"5553 Keebler Drive","homeTown":"Lake Kali","homeCountry":"Cameroon","members":[{"id":"UGVyc29uOjM=","firstName":"Deonte","lastName":"Schmidt","city":"East Raina","state":"OK","country":"Iceland"},{"id":"UGVyc29uOjM2","firstName":"Keagan","lastName":"Halvorson","city":"Jaylenland","state":"OK","country":"Pakistan"},{"id":"UGVyc29uOjM3","firstName":"Stefanie","lastName":"Feeney","city":"Trevionborough","state":"MN","country":"Palestinian Territory"}]},{"id":"31","name":"ReactJS New Jeffmouth","address":"2860 Upton Wells","homeTown":"New Jeffmouth","homeCountry":"Mauritius","members":[{"id":"UGVyc29uOjM3","firstName":"Stefanie","lastName":"Feeney","city":"Trevionborough","state":"MN","country":"Palestinian Territory"},{"id":"UGVyc29uOjE=","firstName":"Ciara","lastName":"Schultz","city":"New Maximillian","state":"NV","country":"Bouvet Island (Bouvetoya)"},{"id":"UGVyc29uOjE1","firstName":"Leonel","lastName":"Pacocha","city":"Stiedemannport","state":"MD","country":"Ghana"}]},{"id":"32","name":"Papers we love, Katlynnberg","address":"348 Crooks Station","homeTown":"Katlynnberg","homeCountry":"Dominica","members":[{"id":"UGVyc29uOjIw","firstName":"Cortney","lastName":"Rowe","city":"Port Arnoldshire","state":"VT","country":"Congo"},{"id":"UGVyc29uOjEx","firstName":"Isai","lastName":"Gerhold","city":"Port Aimeemouth","state":"NC","country":"Democratic People's Republic of Korea"},{"id":"UGVyc29uOjE3","firstName":"Evalyn","lastName":"Wehner","city":"Hintzland","state":"WI","country":"Zambia"}]},{"id":"33","name":"Digital Marketing Poland","address":"63757 Schiller View","homeTown":"Effertzberg","homeCountry":"Poland","members":[{"id":"UGVyc29uOjE0","firstName":"Devan","lastName":"Lindgren","city":"Claudiemouth","state":"NJ","country":"Burundi"},{"id":"UGVyc29uOjEz","firstName":"Alexandria","lastName":"Cummings","city":"Port Lelah","state":"UT","country":"Chile"},{"id":"UGVyc29uOjE4","firstName":"Sherman","lastName":"Ziemann","city":"Port Agustin","state":"GA","country":"Latvia"}]},{"id":"34","name":"Virtual Java User Group","address":"73372 Ron Centers","homeTown":"East Bertbury","homeCountry":"Svalbard & Jan Mayen Islands","members":[{"id":"UGVyc29uOjE1","firstName":"Leonel","lastName":"Pacocha","city":"Stiedemannport","state":"MD","country":"Ghana"},{"id":"UGVyc29uOjM3","firstName":"Stefanie","lastName":"Feeney","city":"Trevionborough","state":"MN","country":"Palestinian Territory"},{"id":"UGVyc29uOjM=","firstName":"Deonte","lastName":"Schmidt","city":"East Raina","state":"OK","country":"Iceland"}]},{"id":"35","name":"West Ociemouth Data Science Beginners Meetup","address":"19302 Heaney Mall","homeTown":"West Ociemouth","homeCountry":"Nigeria","members":[{"id":"UGVyc29uOjIy","firstName":"Dejon","lastName":"Nolan","city":"Turnertown","state":"AZ","country":"Antigua and Barbuda"},{"id":"UGVyc29uOjg=","firstName":"Meda","lastName":"Lynch","city":"East Janport","state":"WV","country":"Mali"},{"id":"UGVyc29uOjI0","firstName":"Karolann","lastName":"Grant","city":"New Margarette","state":"NE","country":"Cocos (Keeling) Islands"}]},{"id":"36","name":"Python United Kingdom","address":"18168 Edd Cliff","homeTown":"Hammesburgh","homeCountry":"United Kingdom","members":[{"id":"UGVyc29uOjI1","firstName":"Rebekah","lastName":"Schinner","city":"Toyborough","state":"HI","country":"Moldova"},{"id":"UGVyc29uOjE1","firstName":"Leonel","lastName":"Pacocha","city":"Stiedemannport","state":"MD","country":"Ghana"},{"id":"UGVyc29uOjM1","firstName":"Janelle","lastName":"Corwin","city":"Jeromeside","state":"CA","country":"Chad"}]},{"id":"37","name":"LJC - London Java Community","address":"2241 Nels Ford","homeTown":"Kuvalisstad","homeCountry":"Bahamas","members":[{"id":"UGVyc29uOjE2","firstName":"Nyasia","lastName":"Nienow","city":"Shanieberg","state":"NE","country":"Guam"},{"id":"UGVyc29uOjEy","firstName":"Katlyn","lastName":"Ferry","city":"Rogersville","state":"NE","country":"Israel"},{"id":"UGVyc29uOjU=","firstName":"Princess","lastName":"Kerluke","city":"Port Mariahstad","state":"VA","country":"French Polynesia"}]},{"id":"38","name":"Lake Karlishire Java 8 Meetup","address":"223 Earnestine Extension","homeTown":"Lake Karlishire","homeCountry":"Afghanistan","members":[{"id":"UGVyc29uOjMx","firstName":"Thelma","lastName":"Metz","city":"North Heberstad","state":"OR","country":"Dominica"},{"id":"UGVyc29uOjU=","firstName":"Princess","lastName":"Kerluke","city":"Port Mariahstad","state":"VA","country":"French Polynesia"},{"id":"UGVyc29uOjM2","firstName":"Keagan","lastName":"Halvorson","city":"Jaylenland","state":"OK","country":"Pakistan"}]},{"id":"39","name":"Docker Annetteberg","address":"5717 Mueller Spring","homeTown":"Annetteberg","homeCountry":"Latvia","members":[{"id":"UGVyc29uOjEz","firstName":"Alexandria","lastName":"Cummings","city":"Port Lelah","state":"UT","country":"Chile"},{"id":"UGVyc29uOjk=","firstName":"Javonte","lastName":"Wilderman","city":"Runteland","state":"MO","country":"Hong Kong"},{"id":"UGVyc29uOjM5","firstName":"Dan","lastName":"Ratke","city":"Alland","state":"NE","country":"Brunei Darussalam"}]}],"locations":[{"id":"0","name":"Rempel Inc","address":"763 Lance Drives","city":"Kundeborough","country":"Australia"},{"id":"1","name":"Hills, Hoeger and O'Connell","address":"54747 Hilda Street","city":"Lake Olenton","country":"San Marino"},{"id":"2","name":"Carter and Sons","address":"0180 Hadley Island","city":"Hilllport","country":"Pakistan"},{"id":"3","name":"Bechtelar Group","address":"19979 Frami Stream","city":"Lake Carleton","country":"Azerbaijan"},{"id":"4","name":"Hane, Daugherty and Connelly","address":"3540 Prohaska Lakes","city":"Port Janae","country":"Saint Barthelemy"},{"id":"5","name":"Runte - Daniel","address":"57838 Brown Hills","city":"New Melyssa","country":"Qatar"},{"id":"6","name":"Reinger - VonRueden","address":"8921 Erick Fords","city":"Farrellborough","country":"Norfolk Island"},{"id":"7","name":"Ledner and Sons","address":"46104 Coleman Drive","city":"New Ursula","country":"Burkina Faso"},{"id":"8","name":"Lubowitz - Hermiston","address":"348 Crooks Station","city":"Katlynnberg","country":"Dominica"},{"id":"9","name":"Turcotte - Ferry","address":"2860 Upton Wells","city":"New Jeffmouth","country":"Mauritius"},{"id":"10","name":"Wintheiser - Huel","address":"1953 Connelly Cliff","city":"Ledaton","country":"Tunisia"},{"id":"11","name":"Halvorson, Watsica and Ritchie","address":"8385 Terry Stravenue","city":"North Otishaven","country":"Libyan Arab Jamahiriya"},{"id":"12","name":"Predovic, Gleichner and McClure","address":"146 Rogahn Forks","city":"Port Destiney","country":"Senegal"},{"id":"13","name":"Johnston - Rodriguez","address":"634 Alfreda Summit","city":"Turnermouth","country":"Equatorial Guinea"},{"id":"14","name":"Schiller Group","address":"1957 Turcotte Springs","city":"Fionabury","country":"Gambia"},{"id":"15","name":"Kertzmann, Vandervort and Kiehn","address":"644 Stacey Course","city":"Port Nicochester","country":"Albania"},{"id":"16","name":"Grady, Rosenbaum and Ruecker","address":"56396 Lindgren Springs","city":"East Cordiastad","country":"Gabon"},{"id":"17","name":"Metz - Conn","address":"100 Rempel Coves","city":"West Augustine","country":"Hungary"},{"id":"18","name":"Hodkiewicz - Langosh","address":"3516 Aufderhar Isle","city":"North April","country":"Cook Islands"},{"id":"19","name":"Oberbrunner, Morissette and Shanahan","address":"38561 Collier Road","city":"West Lexus","country":"Thailand"},{"id":"20","name":"Fahey, Schowalter and Tremblay","address":"86171 Jenkins Prairie","city":"West Lindsey","country":"Togo"},{"id":"21","name":"Cassin LLC","address":"9509 Elda Spur","city":"Schambergerview","country":"Virgin Islands, British"},{"id":"22","name":"Baumbach - Altenwerth","address":"1967 Christiana Rest","city":"Port Velmaville","country":"Montenegro"},{"id":"23","name":"Wolff, Gottlieb and Shanahan","address":"9118 Wuckert Garden","city":"West Daphne","country":"Bahrain"},{"id":"24","name":"Homenick, Kshlerin and Labadie","address":"73372 Ron Centers","city":"East Bertbury","country":"Svalbard & Jan Mayen Islands"},{"id":"25","name":"Bauch - McKenzie","address":"53805 Runolfsdottir Loop","city":"Durwardfurt","country":"Iran"},{"id":"26","name":"Smith and Sons","address":"92710 Bettye Alley","city":"North Kaia","country":"Switzerland"},{"id":"27","name":"Schulist - Leannon","address":"644 Sanford Locks","city":"West Destin","country":"Bhutan"},{"id":"28","name":"Pfannerstill, Lemke and Watsica","address":"297 Gay Ports","city":"Bogisichbury","country":"Pitcairn Islands"},{"id":"29","name":"Treutel - Weber","address":"223 Earnestine Extension","city":"Lake Karlishire","country":"Afghanistan"},{"id":"30","name":"Mosciski and Sons","address":"9128 Kohler Isle","city":"West Andreshaven","country":"Montenegro"},{"id":"31","name":"Schmidt, Vandervort and Bednar","address":"72023 Hagenes Loop","city":"Marleebury","country":"Luxembourg"},{"id":"32","name":"Dach Inc","address":"37972 Jakubowski Summit","city":"West Catharine","country":"South Africa"},{"id":"33","name":"Kreiger Inc","address":"349 Lubowitz Heights","city":"Lake Jordyshire","country":"Northern Mariana Islands"},{"id":"34","name":"Kuvalis, Runte and Dooley","address":"115 Shaun Keys","city":"Claudeberg","country":"Qatar"},{"id":"35","name":"Metz, Schowalter and Brakus","address":"05932 O'Conner Lodge","city":"South Sheldonfort","country":"Croatia"},{"id":"36","name":"Stracke, Adams and Ritchie","address":"611 D'Amore Field","city":"Heaneyburgh","country":"Uruguay"},{"id":"37","name":"Corkery Group","address":"98045 Mayer Island","city":"New Waylonport","country":"Cuba"},{"id":"38","name":"DuBuque - Bruen","address":"477 Zulauf Parkway","city":"Marieside","country":"Albania"},{"id":"39","name":"Boyer and Sons","address":"452 Wehner Landing","city":"Lake Sarahville","country":"Monaco"},{"id":"40","name":"Williamson - Hermann","address":"8113 Rory Greens","city":"Port Ashlee","country":"Reunion"},{"id":"41","name":"Stracke and Sons","address":"2241 Nels Ford","city":"Kuvalisstad","country":"Bahamas"},{"id":"42","name":"Hegmann, Crist and Howe","address":"7460 Rylee Village","city":"New Elsaburgh","country":"Nauru"},{"id":"43","name":"Hauck, Wiza and Rempel","address":"1662 Becker Points","city":"South Michelle","country":"Bosnia and Herzegovina"},{"id":"44","name":"Bashirian Inc","address":"393 Antonietta Circles","city":"South Abbigailside","country":"Malawi"},{"id":"45","name":"Friesen Inc","address":"518 Renee Unions","city":"South Yazminfurt","country":"Luxembourg"},{"id":"46","name":"Erdman - Weissnat","address":"807 Kautzer Ford","city":"South Florence","country":"Gibraltar"},{"id":"47","name":"Kiehn, Wisozk and Krajcik","address":"4337 Roel Forge","city":"New Kyler","country":"El Salvador"},{"id":"48","name":"Rolfson LLC","address":"078 Beier Garden","city":"Lake Amelyberg","country":"Sudan"},{"id":"49","name":"Jones and Sons","address":"630 Borer Canyon","city":"East Abbyville","country":"Nepal"},{"id":"50","name":"Streich, Fisher and Corwin","address":"7076 Barbara Inlet","city":"South Kayceeton","country":"Sweden"},{"id":"51","name":"Beahan, Doyle and Dare","address":"80628 Torrance Fort","city":"Simonisbury","country":"Canada"},{"id":"52","name":"Rice - Littel","address":"2754 Schoen Extensions","city":"Jefferyland","country":"Philippines"},{"id":"53","name":"Shields LLC","address":"30025 Kertzmann Pike","city":"East Babymouth","country":"Liechtenstein"},{"id":"54","name":"Kertzmann, Feil and Bogisich","address":"8881 Estrella Creek","city":"Sauermouth","country":"Guam"},{"id":"55","name":"Cole Group","address":"805 Kozey Fall","city":"Tiaview","country":"Russian Federation"},{"id":"56","name":"Reynolds LLC","address":"63757 Schiller View","city":"Effertzberg","country":"Poland"},{"id":"57","name":"Marvin, Turcotte and Howell","address":"4728 Delmer Village","city":"South Carmel","country":"Saint Vincent and the Grenadines"},{"id":"58","name":"Goyette, Hyatt and Walker","address":"482 Kuhlman Meadows","city":"Hermistonfort","country":"Croatia"},{"id":"59","name":"Connelly, Reinger and Moore","address":"83877 Beatty Ferry","city":"Donview","country":"Belize"},{"id":"60","name":"Heaney LLC","address":"858 Weimann Route","city":"New Murltown","country":"Northern Mariana Islands"},{"id":"61","name":"Sauer - Heller","address":"2748 Bartell Motorway","city":"North Kalistad","country":"Namibia"},{"id":"62","name":"Champlin - Hackett","address":"948 Buford Center","city":"West Lolita","country":"Central African Republic"},{"id":"63","name":"Hagenes, Labadie and Veum","address":"148 Ebert Ferry","city":"Lake Eliton","country":"Iceland"},{"id":"64","name":"Sipes, Dickens and Frami","address":"534 Herman Plaza","city":"Hintzshire","country":"Bolivia"},{"id":"65","name":"Runte LLC","address":"5224 Kenneth Run","city":"Wilmachester","country":"Kyrgyz Republic"},{"id":"66","name":"Champlin - Boyer","address":"029 Rodolfo Stravenue","city":"Macejkovicton","country":"Republic of Korea"},{"id":"67","name":"Deckow Inc","address":"05193 Zander Islands","city":"New Darrylmouth","country":"Ukraine"},{"id":"68","name":"Howe - Moore","address":"199 McDermott Branch","city":"East Francescochester","country":"Antarctica (the territory South of 60 deg S)"},{"id":"69","name":"Herman, Cummerata and Runolfsdottir","address":"266 Gaylord Union","city":"Powlowskiborough","country":"Guyana"},{"id":"70","name":"Ratke - Cormier","address":"4688 Nikolaus Mountains","city":"Dennismouth","country":"Czech Republic"},{"id":"71","name":"Erdman, Moen and Tremblay","address":"56739 Glover Run","city":"Port Avastad","country":"Seychelles"},{"id":"72","name":"Heaney, Braun and Boyer","address":"96181 Kuhic Trail","city":"Humbertofort","country":"Japan"},{"id":"73","name":"Brown Group","address":"85658 Treutel Bypass","city":"East Dustinfurt","country":"Turkmenistan"},{"id":"74","name":"Fritsch - Hegmann","address":"389 Mante Cove","city":"Gerhardland","country":"Kiribati"},{"id":"75","name":"Rowe LLC","address":"2644 Lind Rest","city":"Bridieville","country":"Palestinian Territory"},{"id":"76","name":"Hand, Prosacco and Carroll","address":"789 Klein Lights","city":"Olsonchester","country":"Albania"},{"id":"77","name":"Johns, Cassin and Swift","address":"944 Rachael Viaduct","city":"Laurinebury","country":"Barbados"},{"id":"78","name":"Shields LLC","address":"2294 Meda Pines","city":"Jacynthetown","country":"Bahamas"},{"id":"79","name":"Mertz Group","address":"05941 Lynch Ville","city":"Funkhaven","country":"Micronesia"},{"id":"80","name":"Krajcik, Durgan and Koch","address":"18168 Edd Cliff","city":"Hammesburgh","country":"United Kingdom"},{"id":"81","name":"Gleichner - Cruickshank","address":"33709 Becker Islands","city":"New Marlenville","country":"Poland"},{"id":"82","name":"Zboncak and Sons","address":"3477 Carter Freeway","city":"Horaciobury","country":"Luxembourg"},{"id":"83","name":"Legros, Rohan and Hermiston","address":"42201 Nicolas Passage","city":"Schulistport","country":"Armenia"},{"id":"84","name":"Leuschke LLC","address":"856 Grimes Views","city":"Hintzmouth","country":"Russian Federation"},{"id":"85","name":"Bogan, Von and Emard","address":"7015 Hoppe Trafficway","city":"Blickberg","country":"Faroe Islands"},{"id":"86","name":"Davis, Dickens and Zemlak","address":"989 Keyon Shores","city":"North Kylafurt","country":"Bhutan"},{"id":"87","name":"Sporer Inc","address":"9070 Parker Plaza","city":"Heidenreichmouth","country":"Turkmenistan"},{"id":"88","name":"Hermann, Hintz and Beier","address":"0728 Corwin Lodge","city":"Abbottberg","country":"Jamaica"},{"id":"89","name":"Herzog Inc","address":"5717 Mueller Spring","city":"Annetteberg","country":"Latvia"},{"id":"90","name":"Lueilwitz Group","address":"1266 Ford Plaza","city":"East Sandrinehaven","country":"Zimbabwe"},{"id":"91","name":"Morar - Lind","address":"878 Lehner Ramp","city":"South Elsa","country":"Latvia"},{"id":"92","name":"Kassulke - Ankunding","address":"30261 Streich Key","city":"North Amaraville","country":"Gambia"},{"id":"93","name":"Herman, Heaney and Klocko","address":"19302 Heaney Mall","city":"West Ociemouth","country":"Nigeria"},{"id":"94","name":"Kuhlman Inc","address":"8560 Bashirian Fork","city":"East Evelineton","country":"Gibraltar"},{"id":"95","name":"Ondricka and Sons","address":"896 Velma Manors","city":"South Nickolasfort","country":"Czech Republic"},{"id":"96","name":"Leffler Inc","address":"11362 Bogisich Squares","city":"West Dexter","country":"Brunei Darussalam"},{"id":"97","name":"Simonis, Bode and Maggio","address":"233 Billie Divide","city":"O'Connellbury","country":"Honduras"},{"id":"98","name":"Quitzon - Langosh","address":"5553 Keebler Drive","city":"Lake Kali","country":"Cameroon"},{"id":"99","name":"Cruickshank and Sons","address":"814 Kilback Squares","city":"Rippinton","country":"Estonia"}]}
